just_logger/__init__.py
just_logger/logger.py
just_logger-0.2.1.dist-info/LICENSE
just_logger-0.2.1.dist-info/METADATA
just_logger-0.2.1.dist-info/WHEEL
just_logger-0.2.1.dist-info/top_level.txt
just_logger-0.2.1.dist-info/RECORD
