Metadata-Version: 2.1
Name: just-logger
Version: 0.2.1
Summary: A logging tool is used to record all kinds of logs during program running.
Home-page: https://github.com/Baoming520/just-logger
Author: Baoming Yu
Author-email: dingxuanliang@icloud.com
License-File: LICENSE
